LICENSE
json_write/__init__.py
json_write/py.typed
json_write-0.0.1.2.dist-info/LICENSE
json_write-0.0.1.2.dist-info/METADATA
json_write-0.0.1.2.dist-info/WHEEL
json_write-0.0.1.2.dist-info/RECORD
